Workbook

Sheet 1. Tổng quan
A1: VIP SPORT CENTER – KẾ HOẠCH KIỂM THỬ API BẰNG READYAPI
A3: Dự án | B3: VIP Sport Center – nền tảng quản lý trung tâm thể thao
A4: Kiến trúc | B4: Laravel REST API (backend) + React 18/Vite (frontend) + MySQL 8
A5: Phạm vi test | B5: Chỉ test tầng REST API của backend (nền ReadyAPI). Không test UI React.
A6: Authentication | B6: Laravel Sanctum. Token bearer: Authorization: Bearer <token>
A7: Base URL (ví dụ local) | B7: http://127.0.0.1:8000/api
A8: Ba role | B8: admin, coach, client. Mỗi role có nhánh route riêng (/admin/*, /coach/*, /client/*)
A9: Chức năng chính | B9: Đăng ký/đăng nhập, quản lý client, quản lý coach, kế hoạch tập (planning), thanh toán, bilan sức khỏe, cảnh báo, tài nguyên, xuất PDF biên nhận
A10: Quy tắc bảo mật nổi bật | B10: Khoá tài khoản 30 phút sau 5 lần sai mật khẩu; middleware role; middleware 'locked'
A11: Tool test | B11: SmartBear ReadyAPI (có thể dùng SoapUI OpenSource cho các case cơ bản)
A12: Số test case trong tài liệu này | B12: 32 test case ReadyAPI, phủ 7 nhóm chức năng cốt lõi
A14: GHI CHÚ KHI DỰNG MÔI TRƯỜNG
A15: 1. Chạy backend bằng: cd backend && composer install && cp .env.example .env && php artisan key:generate && php artisan migrate --seed && php artisan serve
A16: 2. Trong ReadyAPI tạo Project 'VIP Sport Center API' kiểu REST. Thêm Environment: Local (baseUrl=http://127.0.0.1:8000/api) và có thể Dev/Stage sau.
A17: 3. Tạo Project Property: baseUrl, adminEmail, adminPassword, coachEmail, coachPassword, clientEmail, clientPassword.
A18: 4. Dùng Property Transfer để lấy token sau mỗi lần login và gán vào Project Property adminToken / coachToken / clientToken.
A19: 5. Mọi request có xác thực dùng Header: Authorization = Bearer ${#Project#adminToken} (thay theo role).
A20: 6. Mỗi test case trong Excel = 1 TestCase trong ReadyAPI (có thể nhóm theo TestSuite theo chức năng).
A21: 7. Dùng Assertion: Valid HTTP Status Codes, JSONPath Match, JSONPath Exists, Response SLA (<= 2000ms), Not SOAP Fault.
A22: 8. Trước khi chạy test ghi/xóa, chuẩn bị DataSource (Excel/CSV) hoặc Groovy script tạo dữ liệu seed.

Sheet 2. Phân vai nhóm
A1: KẾ HOẠCH PHÂN VAI CHO NHÓM 3 NGƯỜI
A2: Tất cả 3 thành viên đều học Tester. Phân chia theo thế mạnh để tối ưu, không ai đứng ngoài test.
A4: Thành viên | B4: Thế mạnh | C4: Vai trò chính trong lab | D4: Deliverable cụ thể
A5: TV1 – giỏi code | B5: Hiểu Laravel, debug nhanh | C5: Test Lead kỹ thuật + viết Groovy scripts trong ReadyAPI | D5: Dựng môi trường (seed DB, chạy artisan serve); viết Groovy script setup/teardown; cấu hình Property Transfer để trích token; code assertion phức tạp (JSONPath); phụ trách TC-AUTH-* và TC-ADMIN-CLIENT-*
A6: TV2 – giỏi tool test | B6: Nắm sâu ReadyAPI, soạn kịch bản | C6: Test Designer + Test Executor chính | D6: Thiết kế bộ 32 test case trong Excel (file này là bản nháp); dựng Project, TestSuite, TestCase trong ReadyAPI; thêm Assertions, DataSource, Load Test; xuất báo cáo HTML; phụ trách TC-COACH-*, TC-PAIEMENT-*, TC-SECURITY-*
A7: TV3 – giỏi slide | B7: Trình bày, bố cục đẹp | C7: Reporter + Presenter + Test Reviewer | D7: Theo dõi tiến độ, cập nhật kết quả vào Excel; chụp screenshot ReadyAPI; soạn slide (15–20 slide) theo cấu trúc gợi ý; thuyết trình phần Demo. Tham gia chạy TC-CLIENT-*, TC-ROLE-* (các case đơn giản để nắm quy trình)
A12: LỊCH LÀM VIỆC GỢI Ý (1 tuần)
A13: Ngày | B13: Hoạt động | C13: Người chịu trách nhiệm | D13: Output
A14: Ngày 1 | B14: Clone repo, dựng backend local, seed DB. Cài ReadyAPI. Review file Excel này cùng nhau | C14: Cả nhóm (TV1 dẫn) | D14: Backend chạy ok ở 127.0.0.1:8000; mọi người login được bằng Postman
A15: Ngày 2 | B15: Tạo Project trong ReadyAPI, thêm Environment, Project Properties, Login + Property Transfer lấy token | C15: TV2 | D15: Project ReadyAPI khung sẵn, token auto refresh
A16: Ngày 3 | B16: Viết test case nhóm Auth (TC-AUTH-01 → 09) | C16: TV1 + TV2 | D16: 9 TC chạy pass
A17: Ngày 4 | B17: Viết test case Admin-Client, Admin-Coach, Paiement | C17: TV2 (TV1 hỗ trợ Groovy) | D17: 13 TC
A18: Ngày 5 | B18: Viết test case Role, Security, Negative cases | C18: TV2 + TV1 | D18: 10 TC
A19: Ngày 6 | B19: Chạy toàn bộ TestRunner, chụp màn hình, xuất báo cáo HTML. TV3 soạn slide | C19: TV3 chủ trì | D19: Báo cáo + draft slide
A20: Ngày 7 | B20: Rehearsal thuyết trình, chỉnh sửa, nộp bài | C20: Cả nhóm | D20: Slide final + Excel final + ReadyAPI project (.xml)
A22: CẤU TRÚC SLIDE GỢI Ý
A23: Slide 1 – Trang bìa: VIP Sport Center – API Testing với ReadyAPI – Nhóm/MSSV
A24: Slide 2 – Giới thiệu dự án: Laravel REST API quản lý trung tâm thể thao, 3 role
A25: Slide 3 – Kiến trúc & công nghệ (Laravel + React + MySQL)
A26: Slide 4 – Phạm vi kiểm thử: tầng API, 7 nhóm chức năng, 32 test case
A27: Slide 5 – Giới thiệu ReadyAPI: khác SoapUI thế nào, các tính năng mạnh (DataSource, Property Transfer, Groovy, Security Test, Load Test)
A28: Slide 6 – Quy trình test: dựng môi trường → tạo Project → viết test → chạy → báo cáo
A29: Slide 7 – Chiến lược thiết kế test: Positive / Negative / Boundary / Security / Role-based
A30: Slide 8 – Nhóm chức năng 1: Authentication (3-4 TC tiêu biểu)
A31: Slide 9 – Nhóm chức năng 2: Admin – Client CRUD
A32: Slide 10 – Nhóm chức năng 3: Payment
A33: Slide 11 – Nhóm chức năng 4: Role-based Access Control (demo 403)
... A38: Slide 16 – Q&A

Sheet 3. Những gì cần test
A1: NHỮNG GÌ CẦN TEST – PHÂN TÍCH SOURCE CODE
A3: Nhóm | B3: Endpoint | C3: Mô tả nghiệp vụ | D3: Rủi ro / Điểm cần kiểm tra | E3: Số TC đề xuất
A4: Authentication | B4: POST /api/login, /register, /logout, /me, /forgot-password, /reset-password | C4: Đăng nhập, đăng ký khách hàng (gán coach ngẫu nhiên theo specialite, tạo cotisation), lấy profile, quên/đặt lại mật khẩu | D4: Khoá tài khoản sau 5 lần sai; trả 423 khi locked; validate email/password; unique email; plan ∈ {mensuel,trimestriel,annuel}; payment_method ∈ {card,cash}; chuyển tiền tự động đúng gói | E4: 9
A5: Admin – Client | B5: GET/POST/PUT/DELETE /api/admin/clients | C5: CRUD client, lọc theo statut/coach_id, tìm kiếm | D5: Phân trang (10/trang); validate coach_id tồn tại; email unique; xóa client phải xóa user kèm theo (cascade); update từng phần (sometimes) | E5: 6
A6: Admin – Coach | B6: GET/POST/PUT/DELETE /api/admin/coaches | C6: CRUD coach, auto sinh code COACH-NNN | D6: Không cho xóa coach còn client; code_coach tăng đúng thứ tự; email unique | E6: 4
A7: Paiement | B7: GET/POST /api/admin/paiements, GET /paiements/stats | C7: Liệt kê échéance, ghi nhận paiement, thống kê theo tháng | D7: Không cho paiement 2 lần cho 1 échéance đã paye; methode ∈ {carte,virement,cheque,especes}; stats tính đúng tổng tháng hiện tại | E7: 4
A8: Coach – Planning | B8: GET /api/coach/planning, POST /planning/seances, POST /seances/{id}/realiser | C8: Lịch tập của coach với client của mình | D8: Coach chỉ thấy client của chính mình; heure_fin > heure_debut; effort_percu 1–10 | E8: 3
A9: Client – Dashboard | B9: GET /api/client/dashboard, /paiements, /planning, /bilans | C9: Client xem thông tin của mình | D9: Client không truy cập được dữ liệu của client khác; không truy cập /admin/* | E9: 3
A10: Role-based security | B10: Tất cả endpoint /admin, /coach, /client | C10: Middleware role + locked | D10: admin truy cập được tất cả; coach truy cập /coach + /client; client chỉ /client; locked user chặn 423; token sai / rỗng → 401 | E10: 3

Sheet 4. Test Cases ReadyAPI
A1: BỘ 32 TEST CASE READYAPI
A2: Cột 'Kết quả' chọn Pass/Fail/Blocked/Not run. Cột 'Assertions' liệt kê các assertion cần thêm trong ReadyAPI.
A4: TC ID | B4: TestSuite | C4: Method | D4: Endpoint | E4: Mục đích | F4: Headers | G4: Request body / Params | H4: Expected Status | I4: Expected Response | J4: Assertions (ReadyAPI) | K4: Loại test | L4: Kết quả | M4: Ghi chú
A5: TC-AUTH-01 | B5: Authentication | C5: POST | D5: /login | E5: Login admin thành công | F5: Content-Type: application/json | G5: {"email":"admin@sportcenter.com","password":"admin123"} | H5: 200 | I5: {token, user:{id,name,email,role:admin}} | J5: Valid HTTP Status 200; JSONPath $.token exists; JSONPath Match $.user.role = admin; Response SLA <= 2000ms | K5: Positive | M5: Dùng Property Transfer gán $.token → Project adminToken
A6: TC-AUTH-02 | B6: Authentication | C6: POST | D6: /login | E6: Login với email không tồn tại | F6: Content-Type: application/json | G6: {"email":"notexist@x.com","password":"any"} | H6: 401 | I6: {message:'Email ou mot de passe incorrect.'} | J6: Status 401; JSONPath Match $.message chứa 'incorrect' | K6: Negative
A7: TC-AUTH-03 | B7: Authentication | C7: POST | D7: /login | E7: Login sai password 1 lần – đếm tentative | F7: Content-Type: application/json | G7: {"email":"test5@sportcenter.com","password":"wrong"} | H7: 401 | I7: {message chứa 'tentative(s) restante(s)'} | J7: Status 401; Contains 'tentative' | K7: Negative | L7: Dùng user test riêng, không dùng admin thật
A8: TC-AUTH-04 | B8: Authentication | C8: POST | D8: /login | E8: Khoá tài khoản sau 5 lần sai → trả 423 | F8: Content-Type: application/json | G8: Lặp 5 lần với password sai, lần 6 dùng password đúng | H8: 423 | I8: {message chứa 'bloqué'} | J8: Status 423; Contains 'bloqué' hoặc 'temporairement' | K8: Boundary/Security | L8: Nên dùng DataSource Loop 5 vòng; teardown reset failed_login_attempts qua Groovy
A9: TC-AUTH-05 | B9: Authentication | C9: POST | D9: /login | E9: Email thiếu – validate 422 | F9: Content-Type: application/json | G9: {"password":"x"} | H9: 422 | I9: {errors.email} | J9: Status 422; JSONPath Exists $.errors.email | K9: Negative
A10: TC-AUTH-06 | B10: Authentication | C10: POST | D10: /register | E10: Đăng ký client gói mensuel bằng thẻ – 201 | F10: Content-Type: application/json | G10: {name, email unique, password>=8, password_confirmation, specialite:'musculation', plan:'mensuel', payment_method:'card'} | H10: 201 | I10: {token, user:{role:client}} | J10: Status 201; JSONPath $.user.role = client; token exists | K10: Positive | L10: Dùng Groovy để sinh email ngẫu nhiên: 'u'+System.currentTimeMillis()+'@test.com'
A11: TC-AUTH-07 | B11: Authentication | C11: POST | D11: /register | E11: Đăng ký với plan không hợp lệ – 422 | F11: Content-Type: application/json | G11: {...plan:'quotidien', payment_method:'card'} | H11: 422 | I11: {errors.plan} | J11: Status 422; JSONPath Exists $.errors.plan | K11: Negative
A12: TC-AUTH-08 | B12: Authentication | C12: GET | D12: /me | E12: Lấy profile khi có token hợp lệ | F12: Authorization: Bearer ${#Project#clientToken} | G12: - | H12: 200 | I12: {id,name,email,role,profile} | J12: Status 200; $.role exists; $.profile not null | K12: Positive
A13: TC-AUTH-09 | B13: Authentication | C13: POST | D13: /logout | E13: Logout thu hồi token | F13: Authorization: Bearer ${#Project#clientToken} | G13: - | H13: 200 | I13: {message:'Déconnexion réussie.'} | J13: Status 200; sau đó gọi lại /me phải trả 401 | K13: Positive | L13: Chain với TC-AUTH-08
A14: TC-ADMIN-CLIENT-01 | B14: Admin - Client | C14: GET | D14: /admin/clients | E14: Admin xem danh sách client, phân trang 10 | F14: Authorization: Bearer ${#Project#adminToken} | G14: - | H14: 200 | I14: Paginated: {data[], current_page, per_page:10, total} | J14: Status 200; $.per_page = 10; $.data array exists | K14: Positive
A15: TC-ADMIN-CLIENT-02 | B15: Admin - Client | C15: GET | D15: /admin/clients?search=Dupont | E15: Tìm kiếm theo tên | F15: Authorization: Bearer ${#Project#adminToken} | G15: Query: search=Dupont | H15: 200 | I15: Chỉ client có nom/prenom chứa Dupont | J15: Status 200; mọi $.data[*].nom hoặc prenom chứa 'Dupont' (Groovy assert) | K15: Positive
A16: TC-ADMIN-CLIENT-03 | B16: Admin - Client | C16: POST | D16: /admin/clients | E16: Admin tạo client mới | F16: Authorization: Bearer ${#Project#adminToken}; Content-Type: application/json | G16: {prenom, nom, email unique, password>=8, coach_id tồn tại, montant_annuel>=0} | H16: 201 | I16: {message, client:{id,user,coach}} | J16: Status 201; JSONPath Exists $.client.id | K16: Positive | L16: Property Transfer $.client.id → createdClientId
A17: TC-ADMIN-CLIENT-04 | B17: Admin - Client | C17: POST | D17: /admin/clients | E17: Tạo client với coach_id không tồn tại – 422 | F17: Authorization: Bearer ${#Project#adminToken} | G17: {coach_id:99999, ...} | H17: 422 | I17: {errors.coach_id} | J17: Status 422; JSONPath Exists $.errors.coach_id | K17: Negative
A18: TC-ADMIN-CLIENT-05 | B18: Admin - Client | C18: PUT | D18: /admin/clients/{id} | E18: Admin cập nhật statut client | F18: Authorization: Bearer ${#Project#adminToken} | G18: {statut:'suspendu'} | H18: 200 | I18: {client.statut:'suspendu'} | J18: Status 200; JSONPath Match $.client.statut = suspendu | K18: Positive | L18: Dùng createdClientId từ TC-03
A19: TC-ADMIN-CLIENT-06 | B19: Admin - Client | C19: DELETE | D19: /admin/clients/{id} | E19: Admin xóa client – xóa luôn user | F19: Authorization: Bearer ${#Project#adminToken} | G19: - | H19: 200 | I19: {message:'Client supprimé.'} | J19: Status 200; sau đó GET /admin/clients/{id} trả 404 | K19: Positive
A20: TC-ADMIN-COACH-01 | B20: Admin - Coach | C20: GET | D20: /admin/coaches | E20: Liệt kê coach, có clients_count | F20: Authorization: Bearer ${#Project#adminToken} | G20: - | H20: 200 | I20: Array of {id, code_coach, clients_count} | J20: Status 200; JSONPath $[0].code_coach exists | K20: Positive
A21: TC-ADMIN-COACH-02 | B21: Admin - Coach | C21: POST | D21: /admin/coaches | E21: Tạo coach mới, auto sinh code_coach | F21: Authorization: Bearer ${#Project#adminToken} | G21: {prenom, nom, email unique, password>=8, specialite:'cardio'} | H21: 201 | I21: {coach.code_coach khớp /^COACH-\d{3}$/} | J21: Status 201; Regex Match $.coach.code_coach = ^COACH-\d{3}$ | K21: Positive
A22: TC-ADMIN-COACH-03 | B22: Admin - Coach | C22: POST | D22: /admin/coaches | E22: Email trùng – 422 | F22: Authorization: Bearer ${#Project#adminToken} | G22: {email:'coach@sportcenter.com', ...} | H22: 422 | I22: {errors.email} | J22: Status 422; JSONPath Exists $.errors.email | K22: Negative
A23: TC-ADMIN-COACH-04 | B23: Admin - Coach | C23: DELETE | D23: /admin/coaches/{id} | E23: Không cho xóa coach còn client – 422 | F23: Authorization: Bearer ${#Project#adminToken} | G23: Chọn coach có client | H23: 422 | I23: {message chứa 'Impossible'} | J23: Status 422; Contains 'Impossible' | K23: Negative/Business rule
A24: TC-PAIEMENT-01 | B24: Paiement | C24: GET | D24: /admin/paiements | E24: Lọc échéance theo statut=retard | F24: Authorization: Bearer ${#Project#adminToken} | G24: Query: statut=retard | H24: 200 | I24: Chỉ échéance en_attente và date_echeance < now | J24: Status 200; Groovy assert date_echeance < today | K24: Positive
A25: TC-PAIEMENT-02 | B25: Paiement | C25: POST | D25: /admin/paiements | E25: Ghi nhận paiement thành công | F25: Authorization: Bearer ${#Project#adminToken} | G25: {echeance_id, montant, methode:'carte', date_paiement} | H25: 201 | I25: {message, paiement:{id}} | J25: Status 201; $.paiement.id exists | K25: Positive
A26: TC-PAIEMENT-03 | B26: Paiement | C26: POST | D26: /admin/paiements | E26: Ghi nhận paiement cho échéance đã paye – 422 | F26: Authorization: Bearer ${#Project#adminToken} | G26: {echeance_id của échéance đã paye} | H26: 422 | I26: {message:'Cette échéance est déjà payée.'} | J26: Status 422; Contains 'déjà payée' | K26: Negative/Business
A27: TC-PAIEMENT-04 | B27: Paiement | C27: GET | D27: /admin/paiements/stats | E27: Thống kê trả về đủ 4 trường | F27: Authorization: Bearer ${#Project#adminToken} | G27: - | H27: 200 | I27: {total_encaisse, total_en_attente, total_en_retard, par_methode[]} | J27: Status 200; JSONPath Exists tất cả 4 field | K27: Positive
A28: TC-COACH-01 | B28: Coach - Planning | C28: GET | D28: /coach/planning | E28: Coach xem planning của mình | F28: Authorization: Bearer ${#Project#coachToken} | G28: Query mois, annee | H28: 200 | I28: {mois, annee, plannings[]} | J28: Status 200; $.plannings exists | K28: Positive
A29: TC-COACH-02 | B29: Coach - Planning | C29: POST | D29: /coach/planning/seances | E29: Coach tạo séance cho client KHÔNG phải của mình – 404 | F29: Authorization: Bearer ${#Project#coachToken} | G29: {client_id của coach khác, date, heure_debut} | H29: 404 | I29: - | J29: Status 404 | K29: Negative/Security
A30: TC-COACH-03 | B30: Coach - Planning | C30: POST | D30: /coach/planning/seances | E30: heure_fin trước heure_debut – 422 | F30: Authorization: Bearer ${#Project#coachToken} | G30: {heure_debut:'10:00', heure_fin:'09:00'} | H30: 422 | I30: {errors.heure_fin} | J30: Status 422; JSONPath Exists $.errors.heure_fin | K30: Boundary
... A37: TC-SECURITY-02 | B37: Security | C37: POST | D37: /register | E37: Password quá ngắn (7 ký tự) – 422 | F37: Content-Type: application/json | G37: {password:'1234567', password_confirmation:'1234567', ...} | H37: 422 | I37: {errors.password} | J37: Status 422; JSONPath Exists $.errors.password | K37: Boundary

Sheet 5. Tổng hợp
A1: TỔNG HỢP KẾT QUẢ
A3: TestSuite | B3: Số TC | C3: Pass | D3: Fail | E3: Blocked / Not run | F3: % Pass
A4: Authentication | B4: =COUNTIF('4. Test Cases ReadyAPI'!$B$5:$B$37,A4) -> 9 | C4: =COUNTIFS('4. Test Cases ReadyAPI'!$B$5:$B$37,A4,'4. Test Cases ReadyAPI'!$L$5:$L$37,"Pass") -> 0 | D4: =COUNTIFS('4. Test Cases ReadyAPI'!$B$5:$B$37,A4,'4. Test Cases ReadyAPI'!$L$5:$L$37,"Fail") -> 0 | E4: =B4-C4-D4 -> 9 | F4: =IF(B4=0,0,C4/B4) -> 0
A5: Admin - Client | B5: =COUNTIF('4. Test Cases ReadyAPI'!$B$5:$B$37,A5) -> 6 | C5: =COUNTIFS('4. Test Cases ReadyAPI'!$B$5:$B$37,A5,'4. Test Cases ReadyAPI'!$L$5:$L$37,"Pass") -> 0 | D5: =COUNTIFS('4. Test Cases ReadyAPI'!$B$5:$B$37,A5,'4. Test Cases ReadyAPI'!$L$5:$L$37,"Fail") -> 0 | E5: =B5-C5-D5 -> 6 | F5: =IF(B5=0,0,C5/B5) -> 0
A6: Admin - Coach | B6: =COUNTIF('4. Test Cases ReadyAPI'!$B$5:$B$37,A6) -> 4 | C6: =COUNTIFS('4. Test Cases ReadyAPI'!$B$5:$B$37,A6,'4. Test Cases ReadyAPI'!$L$5:$L$37,"Pass") -> 0 | D6: =COUNTIFS('4. Test Cases ReadyAPI'!$B$5:$B$37,A6,'4. Test Cases ReadyAPI'!$L$5:$L$37,"Fail") -> 0 | E6: =B6-C6-D6 -> 4 | F6: =IF(B6=0,0,C6/B6) -> 0
A7: Paiement | B7: =COUNTIF('4. Test Cases ReadyAPI'!$B$5:$B$37,A7) -> 4 | C7: =COUNTIFS('4. Test Cases ReadyAPI'!$B$5:$B$37,A7,'4. Test Cases ReadyAPI'!$L$5:$L$37,"Pass") -> 0 | D7: =COUNTIFS('4. Test Cases ReadyAPI'!$B$5:$B$37,A7,'4. Test Cases ReadyAPI'!$L$5:$L$37,"Fail") -> 0 | E7: =B7-C7-D7 -> 4 | F7: =IF(B7=0,0,C7/B7) -> 0
A8: Coach - Planning | B8: =COUNTIF('4. Test Cases ReadyAPI'!$B$5:$B$37,A8) -> 3 | C8: =COUNTIFS('4. Test Cases ReadyAPI'!$B$5:$B$37,A8,'4. Test Cases ReadyAPI'!$L$5:$L$37,"Pass") -> 0 | D8: =COUNTIFS('4. Test Cases ReadyAPI'!$B$5:$B$37,A8,'4. Test Cases ReadyAPI'!$L$5:$L$37,"Fail") -> 0 | E8: =B8-C8-D8 -> 3 | F8: =IF(B8=0,0,C8/B8) -> 0
A9: Client - Dashboard | B9: =COUNTIF('4. Test Cases ReadyAPI'!$B$5:$B$37,A9) -> 2 | C9: =COUNTIFS('4. Test Cases ReadyAPI'!$B$5:$B$37,A9,'4. Test Cases ReadyAPI'!$L$5:$L$37,"Pass") -> 0 | D9: =COUNTIFS('4. Test Cases ReadyAPI'!$B$5:$B$37,A9,'4. Test Cases ReadyAPI'!$L$5:$L$37,"Fail") -> 0 | E9: =B9-C9-D9 -> 2 | F9: =IF(B9=0,0,C9/B9) -> 0
A10: Role Security | B10: =COUNTIF('4. Test Cases ReadyAPI'!$B$5:$B$37,A10) -> 3 | C10: =COUNTIFS('4. Test Cases ReadyAPI'!$B$5:$B$37,A10,'4. Test Cases ReadyAPI'!$L$5:$L$37,"Pass") -> 0 | D10: =COUNTIFS('4. Test Cases ReadyAPI'!$B$5:$B$37,A10,'4. Test Cases ReadyAPI'!$L$5:$L$37,"Fail") -> 0 | E10: =B10-C10-D10 -> 3 | F10: =IF(B10=0,0,C10/B10) -> 0
A11: Security | B11: =COUNTIF('4. Test Cases ReadyAPI'!$B$5:$B$37,A11) -> 2 | C11: =COUNTIFS('4. Test Cases ReadyAPI'!$B$5:$B$37,A11,'4. Test Cases ReadyAPI'!$L$5:$L$37,"Pass") -> 0 | D11: =COUNTIFS('4. Test Cases ReadyAPI'!$B$5:$B$37,A11,'4. Test Cases ReadyAPI'!$L$5:$L$37,"Fail") -> 0 | E11: =B11-C11-D11 -> 2 | F11: =IF(B11=0,0,C11/B11) -> 0
A12: TỔNG | B12: =SUM(B4:B11) -> 33 | C12: =SUM(C4:C11) -> 0 | D12: =SUM(D4:D11) -> 0 | E12: =SUM(E4:E11) -> 33 | F12: =IF(B12=0,0,C12/B12) -> 0

Sheet NFR Overview
A1: Mục | B1: Nội dung
A2: Scope | B2: 33 original functional cases + 17 new NFR cases = 50; NFR includes 6 performance + 11 targeted security cases.
A3: Status | B3: Requirements/thresholds proposed for LAB. Existing functional cases unchanged. Original sheets are preserved.
A4: Node HTTP | B4: {"total":17,"pass":14,"fail":3,"blocked":0} | 2026-10-05T07:38:22.125Z
A5: Groovy scripts | B5: {"total":17,"pass":13,"fail":4,"blocked":0} | 2026-10-05T07:44:17.498Z
A6: ReadyAPI Desktop | B6: Not run. XML schema/standalone Groovy evidence is NOT GUI evidence.
A7: Environment | B7: { "managed": true, "database": "fresh isolated seeded SQLite", "server": "PHP built-in single-worker development server", "php": "8.2.12", "node": "v24.12.0", "os": "win32 10.0.26200", "cpu": "AMD Ryzen 7 H 255 w/ Radeon 780M Graphics", "logicalCpus": 16, "memoryGB": 30.8, "bcryptRounds": 4 }
A8: Thresholds | B8: p95: baseline 500ms; small load/mixed/stats 1000ms; spike 1500ms; short soak 750ms. All max 2000ms, errors 0. Not production SLOs.
A9: Measurement | B9: Full body latency with monotonic clock. Nearest-rank percentile. Main sample only; login/warmup/cleanup excluded. Throughput includes pacing.
A10: NFR variables | B10: Descriptions uniqueEmail/qaId/newSessionId/UTCtoday/role credentials are dynamic native script variables, not literal JSON values. Refer script for HTTP wire body. Standard admin fixture text applies only to cases that create a client; other cases follow the setup stated first.
A11: Safety | B11: localhost only; explicit nfrLabOnly=true; max5 workers, <=100 requests per phase, timeout5s. Login burst <=25, nonexistent QA email only.
A12: Isolation | B12: Managed mode creates fresh SQLite, migrate/seed, single-worker PHP server, BCRYPT_ROUNDS=4. Retains QA DB for evidence; stops owned server.
... A23: SmartBear source | B23: https://support.smartbear.com/readyapi/getting-started/performance-testing/customizing-a-performance-test-part-1/

Sheet NFR Cases
A1: TC ID | B1: Category | C1: Objective | D1: Requirement / proposed policy | E1: OWASP mapping | F1: Profile / fixtures | G1: Method / endpoints | H1: Expected / thresholds | I1: Assertions | J1: Cleanup / scope | K1: Node HTTP | L1: Groovy script | M1: ReadyAPI GUI | N1: Candidate defect | O1: Actual evidence
A2: TC-NFR-PERF-01 | B2: Performance | C2: Baseline /me: latency distribution | D2: LAB target proposed by test team; validate with lecturer/product owner. | E2: N/A | F2: {"routes":[{"role":"client","path":"/me"}],"warmup":5,"count":30,"concurrency":1} | G2: GET /me (client) | H2: HTTP 200 + correct payload; p95 <= 500ms; max <= 2000ms; errorRate = 0. | I2: Status + payload for every sample; p50/p95/p99/max/RPS/errors; recovery per phase; min samples. | J2: QA client soft delete + logout issued tokens. Only lab DB; sessions/cotisations may remain. | K2: Pass | L2: Pass | M2: Not run | O2: { "metrics": { "percentileMethod": "nearest-rank", "phases": [ { "phase": "measured", "concurrency": 1, "requests": 30, "errors": 0, "errorRate": 0, "p50Ms": 117.39, "p95Ms": 149.25, "p99Ms": 151.57, "maxMs": 151.57, "elapsedMs": 3767, "throughputRps": 7.96 } ] }, "observations": {}, "error": null }
A3: TC-NFR-PERF-02 | B3: Performance | C3: Small concurrent load: admin client list | D3: LAB target proposed by test team; validate with lecturer/product owner. | E3: N/A | F3: {"routes":[{"role":"admin","path":"/admin/clients"}],"warmup":5,"count":50,"concurrency":5} | G3: GET /admin/clients (admin) | H3: HTTP 200 + correct payload; p95 <= 1000ms; max <= 2000ms; errorRate = 0. | I3: Status + payload for every sample; p50/p95/p99/max/RPS/errors; recovery per phase; min samples. | J3: QA client soft delete + logout issued tokens. Only lab DB; sessions/cotisations may remain. | K3: Pass | L3: Fail | M3: Not run | O3: { "metrics": { "percentileMethod": "nearest-rank", "phases": [ { "phase": "measured", "concurrency": 5, "requests": 50, "errors": 0, "errorRate": 0, "p50Ms": 793.62, "p95Ms": 805.94, "p99Ms": 810.14, "maxMs": 810.14, "elapsedMs": 7943, "throughputRps": 6.3 } ] }, "observations": {}, "error": null }
A4: TC-NFR-PERF-03 | B4: Performance | C4: Mixed roles, read-only workload | D4: LAB target proposed by test team; validate with lecturer/product owner. | E4: N/A | F4: {"routes":[{"role":"admin","path":"/admin/clients"},{"role":"coach","path":"/coach/clients"},{"role":"client","path":"/client/paiements"}],"warmup":5,"count":60,"concurrency":3} | G4: GET /admin/clients (admin) GET /coach/clients (coach) GET /client/paiements (client) | H4: HTTP 200 + correct payload; p95 <= 1000ms; max <= 2000ms; errorRate = 0. | I4: Status + payload for every sample; p50/p95/p99/max/RPS/errors; recovery per phase; min samples. | J4: QA client soft delete + logout issued tokens. Only lab DB; sessions/cotisations may remain. | K4: Pass | L4: Pass | M4: Not run | O4: { "metrics": { "percentileMethod": "nearest-rank", "phases": [ { "phase": "measured", "concurrency": 3, "requests": 60, "errors": 0, "errorRate": 0, "p50Ms": 464.81, "p95Ms": 485.38, "p99Ms": 490.2, "maxMs": 490.2, "elapsedMs": 9300, "throughputRps": 6.45 } ] }, "observations": {}, "error": null }
A5: TC-NFR-PERF-04 | B5: Performance | C5: Payment stats aggregation at small load | D5: LAB target proposed by test team; validate with lecturer/product owner. | E5: N/A | F5: {"routes":[{"role":"admin","path":"/admin/paiements/stats"}],"warmup":5,"count":30,"concurrency":3} | G5: GET /admin/paiements/stats (admin) | H5: HTTP 200 + correct payload; p95 <= 1000ms; max <= 2000ms; errorRate = 0. | I5: Status + payload for every sample; p50/p95/p99/max/RPS/errors; recovery per phase; min samples. | J5: QA client soft delete + logout issued tokens. Only lab DB; sessions/cotisations may remain. | K5: Pass | L5: Pass | M5: Not run | O5: { "metrics": { "percentileMethod": "nearest-rank", "phases": [ { "phase": "measured", "concurrency": 3, "requests": 30, "errors": 0, "errorRate": 0, "p50Ms": 419.41, "p95Ms": 429.91, "p99Ms": 430.43, "maxMs": 430.43, "elapsedMs": 4203, "throughputRps": 7.14 } ] }, "observations": {}, "error": null }
A6: TC-NFR-PERF-05 | B6: Performance | C6: Bounded spike and recovery | D6: LAB target proposed by test team; validate with lecturer/product owner. | E6: N/A | F6: {"routes":[{"role":"admin","path":"/admin/clients"}],"warmup":5,"count":80,"concurrency":5,"phases":[{"name":"baseline","count":20,"concurrency":1},{"name":"spike","count":40,"concurrency":5},{"name":"recovery","count":20,"concurrency":1}]} | G6: GET /admin/clients (admin) | H6: HTTP 200 + correct payload; p95 <= 1500ms; max <= 2000ms; errorRate = 0. Recovery p95 <= max(500ms, 3 * baseline p95). | I6: Status + payload for every sample; p50/p95/p99/max/RPS/errors; recovery per phase; min samples. | J6: QA client soft delete + logout issued tokens. Only lab DB; sessions/cotisations may remain. | K6: Pass | L6: Pass | M6: Not run | O6: { "metrics": { "percentileMethod": "nearest-rank", "phases": [ { "phase": "baseline", "concurrency": 1, "requests": 20, "errors": 0, "errorRate": 0, "p50Ms": 158.27, "p95Ms": 169.71, "p99Ms": 171.98, "maxMs": 171.98, "elapsedMs": 3215, "throughputRps": 6.22 }, { "phase": "spike", "concurrency": 5, "requests": 40, "errors": 0, "errorRate": 0, "p50Ms": 793.78, "p95Ms": 804.72, "p99Ms": 805.89, "maxMs": 805.89, "elapsedMs": 6366, "throughputRps": 6.28 }, { "phase": "recovery", "concurrency": 1, "requests": 20, "errors": 0, "errorRate": 0, "p50Ms": 157.48, "p95Ms": 166.21, "p99Ms": 168.13, "maxMs": 168.13, "elapsedMs": 3174, "throughputRps": 6.3 } ], "recoveryLimitMs": 509.13 }, "observations": {}, "error": null }
A7: TC-NFR-PERF-06 | B7: Performance | C7: Short soak: 20 seconds, bounded requests | D7: LAB target proposed by test team; validate with lecturer/product owner. | E7: N/A | F7: {"routes":[{"role":"client","path":"/me"}],"warmup":5,"count":80,"concurrency":1,"durationMs":20000,"paceMs":250,"minimumSamples":20} | G7: GET /me (client) | H7: HTTP 200 + correct payload; p95 <= 750ms; max <= 2000ms; errorRate = 0. | I7: Status + payload for every sample; p50/p95/p99/max/RPS/errors; recovery per phase; min samples. | J7: QA client soft delete + logout issued tokens. Only lab DB; sessions/cotisations may remain. | K7: Pass | L7: Pass | M7: Not run | O7: { "metrics": { "percentileMethod": "nearest-rank", "phases": [ { "phase": "measured", "concurrency": 1, "requests": 79, "errors": 0, "errorRate": 0, "p50Ms": 142.55, "p95Ms": 154.16, "p99Ms": 158.95, "maxMs": 158.95, "elapsedMs": 20033, "throughputRps": 3.94 } ] }, "observations": {}, "error": null }
A8: TC-NFR-SEC-01 | B8: Security | C8: Fabricated Bearer token must be rejected | D8: Reject unauthenticated API access. | E8: OWASP API2:2023 | F8: No login required. | G8: GET /me; Bearer 999999|not-a-real-token; no body. | H8: GET /me = 401; no user/profile data. | I8: Exact HTTP/access result + token/role/state/recursive JSON checks. See code action for all requests. | J8: QA client soft delete + logout issued tokens. Only lab DB; sessions/cotisations may remain. | K8: Pass | L8: Pass | M8: Not run | O8: { "metrics": null, "observations": {}, "error": null }
A9: TC-NFR-SEC-02 | B9: Security | C9: Altered token must be rejected | D9: Token secret integrity must be enforced. | E9: OWASP API2:2023 | F9: Login client seed, retain original token; modify last secret character. | G9: POST /login {email:clientEmail,password:clientPassword}; GET /me with changed token; GET /me with original token. | H9: One-character changed token -> 401; original token still works. | I9: Exact HTTP/access result + token/role/state/recursive JSON checks. See code action for all requests. | J9: QA client soft delete + logout issued tokens. Only lab DB; sessions/cotisations may remain. | K9: Pass | L9: Pass | M9: Not run | O9: { "metrics": null, "observations": {}, "error": null }
A10: TC-NFR-SEC-03 | B10: Security | C10: Revoked token cannot be replayed | D10: Logout invalidates this session token. | E10: OWASP API2:2023 | F10: Issue dedicated client token; do not reuse other case tokens. | G10: POST /login {email:clientEmail,password:clientPassword}; POST /logout with new token; GET /me with same revoked token. | H10: Login 200; logout 200; reused token /me 401. | I10: Exact HTTP/access result + token/role/state/recursive JSON checks. See code action for all requests. | J10: QA client soft delete + logout issued tokens. Only lab DB; sessions/cotisations may remain. | K10: Pass | L10: Pass | M10: Not run | O10: { "metrics": null, "observations": {}, "error": null }
A11: TC-NFR-SEC-04 | B11: Security | C11: Role matrix blocks privileged reads and writes | D11: Client/coach cannot act as admin. | E11: OWASP API5:2023 | F11: Admin creates UUID QA client assigned to Karim; login admin/coach/client independently. Admin fixture: GET coach /me -> POST admin/clients {prenom:"NFR",nom:"QA",email:uniqueEmail,password:"Password123!",coach_id:ownerProfileId,montant_annuel:3600}. Tokens/IDs from this case only. | G11: GET /admin/clients as client then coach; PUT /admin/clients/{qaId} as client with {statut:"suspendu"}; GET same client as admin; require statut="actif". | H11: Client and coach admin reads 403; client PUT 403; QA client state unchanged. | I11: Exact HTTP/access result + token/role/state/recursive JSON checks. See code action for all requests. | J11: QA client soft delete + logout issued tokens. Only lab DB; sessions/cotisations may remain. | K11: Pass | L11: Pass | M11: Not run | O11: { "metrics": null, "observations": {}, "error": null }
A12: TC-NFR-SEC-05 | B12: Security | C12: Registration role injection cannot grant admin | D12: Public registration always grants client role. | E12: OWASP API3:2023 | F12: UUID email; admin token for cleanup only; register cash avoids payment mutation. | G12: POST /register {name:"NFR QA",email:uniqueEmail,password:"Password123!",password_confirmation:"Password123!",specialite:"Musculation",plan:"mensuel",payment_method:"cash",role:"admin",active:true}; GET /me with returned token; GET /admin/clients with same token. | H12: Submitted role=admin ignored/rejected; if created: /me role=client and admin access 403. | I12: Exact HTTP/access result + token/role/state/recursive JSON checks. See code action for all requests. | J12: QA client soft delete + logout issued tokens. Only lab DB; sessions/cotisations may remain. | K12: Pass | L12: Pass | M12: Not run | O12: { "metrics": null, "observations": {}, "error": null }
A13: TC-NFR-SEC-06 | B13: Security | C13: Coach cannot read another coach client assessment | D13: Assessments accessible only to assigned coach. | E13: OWASP API1:2023 | F13: Admin creates UUID QA client assigned to Sara (otherCoach); login Sara and Karim separately. Admin fixture: GET coach /me -> POST admin/clients {prenom:"NFR",nom:"QA",email:uniqueEmail,password:"Password123!",coach_id:ownerProfileId,montant_annuel:3600}. Tokens/IDs from this case only. | G13: GET /coach/clients/{qaId}/bilans as Sara (owner control200), then same URL as Karim (403/404). | H13: Owner read 200; other coach read 403 or 404; no assessment data. | I13: Exact HTTP/access result + token/role/state/recursive JSON checks. See code action for all requests. | J13: QA client soft delete + logout issued tokens. Only lab DB; sessions/cotisations may remain. | K13: Pass | L13: Pass | M13: Not run | O13: { "metrics": null, "observations": {}, "error": null }
A14: TC-NFR-SEC-07 | B14: Security | C14: Coach cannot mark another coach session completed | D14: Session write must verify planning.coach_id. | E14: OWASP API1:2023 | F14: Login Sara/Karim; read current-month planning as Sara; reuse an existing seeded planning/client. Create new QA session, never a seed session. | G14: GET /coach/planning?mois={UTCmonth}&annee={UTCyear} as Sara; POST /coach/planning/seances as Sara {client_id:ownerPlanning.client_id,date:UTCtoday,heure_debut:"10:00",heure_fin:"11:00",lieu:"NFR QA",notes:uniqueEmail}; GET planning before; POST /coach/seances/{newSessionId}/realiser as Karim {present:true,effort_percu:5,remarques_coach:"NFR unauthorized probe"}; GET planning as Sara after; compare seance_realisee. | H14: Reuse owner seed planning; create new QA session 201; foreign coach POST 403/404; seanceRealisee remains null. | I14: Exact HTTP/access result + token/role/state/recursive JSON checks. See code action for all requests. | J14: QA client soft delete + logout issued tokens. Only lab DB; sessions/cotisations may remain. | K14: Fail | L14: Fail | M14: Not run | N14: NFR-BUG-001 | O14: { "metrics": null, "observations": { "attemptedStatus": 200, "foreignWritePersisted": true }, "error": "BOLA: foreign coach write accepted or persisted; HTTP=200, persisted=true" }
A15: TC-NFR-SEC-08 | B15: Security | C15: No password/hash/remember_token disclosure in JSON | D15: Responses must exclude authentication secrets at any nesting level. | E15: OWASP API3:2023 | F15: Admin creates UUID QA client; retain admin token for all three reads. Admin fixture: GET coach /me -> POST admin/clients {prenom:"NFR",nom:"QA",email:uniqueEmail,password:"Password123!",coach_id:ownerProfileId,montant_annuel:3600}. Tokens/IDs from this case only. | G15: GET /me; GET /admin/clients; GET /admin/clients/{qaId}; recursively inspect JSON field names, no raw response persisted. | H15: Recursive key check on /me, admin list and QA detail; no password, password_hash, remember_token, access_token or token. | I15: Exact HTTP/access result + token/role/state/recursive JSON checks. See code action for all requests. | J15: QA client soft delete + logout issued tokens. Only lab DB; sessions/cotisations may remain. | K15: Pass | L15: Pass | M15: Not run | O15: { "metrics": null, "observations": {}, "error": null }
A16: TC-NFR-SEC-09 | B16: Security | C16: Errors do not expose SQL, stack or source paths | D16: Debug details must be suppressed (APP_DEBUG=false). | E16: OWASP API8:2023 | F16: APP_DEBUG=false, admin token only for protected missing-client URL. | G16: POST /login {}; GET /admin/clients/2147483647 as admin; GET /nfr-route-not-found without token. Expected422/404/404. | H16: Invalid login 422, missing client 404 and unknown API 404; JSON with no trace/exception/file/SQLSTATE. | I16: Exact HTTP/access result + token/role/state/recursive JSON checks. See code action for all requests. | J16: QA client soft delete + logout issued tokens. Only lab DB; sessions/cotisations may remain. | K16: Pass | L16: Pass | M16: Not run | O16: { "metrics": null, "observations": {}, "error": null }
A17: TC-NFR-SEC-10 | B17: Security | C17: Login does not reveal email existence | D17: PROPOSED: invalid credentials should have indistinguishable public status/message. | E17: OWASP API2:2023 | F17: Admin creates UUID QA client; wrong-password only once, never seed account. Admin fixture: GET coach /me -> POST admin/clients {prenom:"NFR",nom:"QA",email:uniqueEmail,password:"Password123!",coach_id:ownerProfileId,montant_annuel:3600}. Tokens/IDs from this case only. | G17: POST /login {email:"absent-"+uniqueEmail,password:"Wrong123!"}; POST /login {email:uniqueEmail,password:"Wrong123!"}; compare public status/message. | H17: Unknown email and wrong password on QA account both 401 with identical message; this is not a timing side-channel test. | I17: Exact HTTP/access result + token/role/state/recursive JSON checks. See code action for all requests. | J17: QA client soft delete + logout issued tokens. Only lab DB; sessions/cotisations may remain. | K17: Fail | L17: Fail | M17: Not run | N17: NFR-BUG-002 | O17: { "metrics": null, "observations": { "unknownStatus": 401, "knownStatus": 401, "unknownMessage": "Incorrect email or password.", "knownMessage": "Incorrect password. 4 attempt(s) remaining." }, "error": "PROPOSED policy: account enumeration via different error messages\n+ actual - expected\n\n+ 'Incorrect email or password.'\n- 'Incorrect password. 4 attempt(s) remaining.'\n ^\n" }
A18: TC-NFR-SEC-11 | B18: Security | C18: Bounded login burst is throttled | D18: PROPOSED LAB policy: <=20 failed login attempts/minute/source; 429 by request 25. | E18: OWASP API4:2023 | F18: Unique nonexistent QA email. No seeded-account login; max25 sequential requests, stop on first429. | G18: Repeat POST /login {email:uniqueEmail,password:"Wrong123!"}; expect429 by request25 and positive Retry-After. | H18: At most 25 sequential attempts with nonexistent unique email; at least one 429 and positive Retry-After. No real user lockout. | I18: Exact HTTP/access result + token/role/state/recursive JSON checks. See code action for all requests. | J18: QA client soft delete + logout issued tokens. Only lab DB; sessions/cotisations may remain. | K18: Fail | L18: Fail | M18: Not run | N18: NFR-BUG-003 | O18: { "metrics": null, "observations": { "attempts": 25, "throttled": false, "retryAfter": null }, "error": "PROPOSED lab anti-abuse policy: no 429 in bounded 25-request login burst" }

Sheet NFR Results
A1: TC ID | B1: Node HTTP | C1: Groovy script | D1: ReadyAPI GUI | E1: Node metrics / observations | F1: Groovy metrics / observations | G1: Run timestamps | H1: Actual error
A2: TC-NFR-PERF-01 | B2: Pass | C2: Pass | D2: Not run | E2: { "percentileMethod": "nearest-rank", "phases": [ { "phase": "measured", "concurrency": 1, "requests": 30, "errors": 0, "errorRate": 0, "p50Ms": 117.39, "p95Ms": 149.25, "p99Ms": 151.57, "maxMs": 151.57, "elapsedMs": 3767, "throughputRps": 7.96 } ] } | F2: { "percentileMethod": "nearest-rank", "phases": [ { "phase": "measured", "concurrency": 1, "requests": 30, "errors": 0, "errorRate": 0, "p50Ms": 121.66, "p95Ms": 199.39, "p99Ms": 222.24, "maxMs": 222.24, "elapsedMs": 4045, "throughputRps": 7.42 } ] } | G2: 2026-10-05T07:38:22.125Z 2026-10-05T07:44:17.498Z
A3: TC-NFR-PERF-02 | B3: Pass | C3: Fail | D3: Not run | E3: { "percentileMethod": "nearest-rank", "phases": [ { "phase": "measured", "concurrency": 5, "requests": 50, "errors": 0, "errorRate": 0, "p50Ms": 793.62, "p95Ms": 805.94, "p99Ms": 810.14, "maxMs": 810.14, "elapsedMs": 7943, "throughputRps": 6.3 } ] } | F3: { "percentileMethod": "nearest-rank", "phases": [ { "phase": "measured", "concurrency": 5, "requests": 50, "errors": 0, "errorRate": 0, "p50Ms": 949.04, "p95Ms": 1049.27, "p99Ms": 1071.79, "maxMs": 1071.79, "elapsedMs": 9624, "throughputRps": 5.2 } ] } | G3: 2026-10-05T07:38:22.125Z 2026-10-05T07:44:17.498Z | H3: p95 exceeds proposed lab target. Expression: (p.p95Ms <= scenario.p95Ms)
A4: TC-NFR-PERF-03 | B4: Pass | C4: Pass | D4: Not run | E4: { "percentileMethod": "nearest-rank", "phases": [ { "phase": "measured", "concurrency": 3, "requests": 60, "errors": 0, "errorRate": 0, "p50Ms": 464.81, "p95Ms": 485.38, "p99Ms": 490.2, "maxMs": 490.2, "elapsedMs": 9300, "throughputRps": 6.45 } ] } | F4: { "percentileMethod": "nearest-rank", "phases": [ { "phase": "measured", "concurrency": 3, "requests": 60, "errors": 0, "errorRate": 0, "p50Ms": 571, "p95Ms": 616.68, "p99Ms": 696.09, "maxMs": 696.09, "elapsedMs": 11439, "throughputRps": 5.24 } ] } | G4: 2026-10-05T07:38:22.125Z 2026-10-05T07:44:17.498Z
A5: TC-NFR-PERF-04 | B5: Pass | C5: Pass | D5: Not run | E5: { "percentileMethod": "nearest-rank", "phases": [ { "phase": "measured", "concurrency": 3, "requests": 30, "errors": 0, "errorRate": 0, "p50Ms": 419.41, "p95Ms": 429.91, "p99Ms": 430.43, "maxMs": 430.43, "elapsedMs": 4203, "throughputRps": 7.14 } ] } | F5: { "percentileMethod": "nearest-rank", "phases": [ { "phase": "measured", "concurrency": 3, "requests": 30, "errors": 0, "errorRate": 0, "p50Ms": 527.83, "p95Ms": 602.84, "p99Ms": 631.85, "maxMs": 631.85, "elapsedMs": 5363, "throughputRps": 5.59 } ] } | G5: 2026-10-05T07:38:22.125Z 2026-10-05T07:44:17.498Z
A6: TC-NFR-PERF-05 | B6: Pass | C6: Pass | D6: Not run | E6: { "percentileMethod": "nearest-rank", "phases": [ { "phase": "baseline", "concurrency": 1, "requests": 20, "errors": 0, "errorRate": 0, "p50Ms": 158.27, "p95Ms": 169.71, "p99Ms": 171.98, "maxMs": 171.98, "elapsedMs": 3215, "throughputRps": 6.22 }, { "phase": "spike", "concurrency": 5, "requests": 40, "errors": 0, "errorRate": 0, "p50Ms": 793.78, "p95Ms": 804.72, "p99Ms": 805.89, "maxMs": 805.89, "elapsedMs": 6366, "throughputRps": 6.28 }, { "phase": "recovery", "concurrency": 1, "requests": 20, "errors": 0, "errorRate": 0, "p50Ms": 157.48, "p95Ms": 166.21, "p99Ms": 168.13, "maxMs": 168.13, "elapsedMs": 3174, "throughputRps": 6.3 } ], "recoveryLimitMs": 509.13 } | F6: { "percentileMethod": "nearest-rank", "phases": [ { "phase": "baseline", "concurrency": 1, "requests": 20, "errors": 0, "errorRate": 0, "p50Ms": 177.79, "p95Ms": 207.66, "p99Ms": 248.21, "maxMs": 248.21, "elapsedMs": 3697, "throughputRps": 5.41 }, { "phase": "spike", "concurrency": 5, "requests": 40, "errors": 0, "errorRate": 0, "p50Ms": 956.74, "p95Ms": 1011.43, "p99Ms": 1022.67, "maxMs": 1022.67, "elapsedMs": 7697, "throughputRps": 5.2 }, { "phase": "recovery", "concurrency": 1, "requests": 20, "errors": 0, "errorRate": 0, "p50Ms": 191.65, "p95Ms": 223.9, "p99Ms": 226.32, "maxMs": 226.32, "elapsedMs": 3843, "throughputRps": 5.2 } ], "recoveryLimitMs": 622.98 } | G6: 2026-10-05T07:38:22.125Z 2026-10-05T07:44:17.498Z
A7: TC-NFR-PERF-06 | B7: Pass | C7: Pass | D7: Not run | E7: { "percentileMethod": "nearest-rank", "phases": [ { "phase": "measured", "concurrency": 1, "requests": 79, "errors": 0, "errorRate": 0, "p50Ms": 142.55, "p95Ms": 154.16, "p99Ms": 158.95, "maxMs": 158.95, "elapsedMs": 20033, "throughputRps": 3.94 } ] } | F7: { "percentileMethod": "nearest-rank", "phases": [ { "phase": "measured", "concurrency": 1, "requests": 79, "errors": 0, "errorRate": 0, "p50Ms": 179.56, "p95Ms": 206.99, "p99Ms": 215.32, "maxMs": 215.32, "elapsedMs": 20136, "throughputRps": 3.92 } ] } | G7: 2026-10-05T07:38:22.125Z 2026-10-05T07:44:17.498Z
A8: TC-NFR-SEC-01 | B8: Pass | C8: Pass | D8: Not run | E8: {} | F8: {} | G8: 2026-10-05T07:38:22.125Z 2026-10-05T07:44:17.498Z
A9: TC-NFR-SEC-02 | B9: Pass | C9: Pass | D9: Not run | E9: {} | F9: {} | G9: 2026-10-05T07:38:22.125Z 2026-10-05T07:44:17.498Z
A10: TC-NFR-SEC-03 | B10: Pass | C10: Pass | D10: Not run | E10: {} | F10: {} | G10: 2026-10-05T07:38:22.125Z 2026-10-05T07:44:17.498Z
A11: TC-NFR-SEC-04 | B11: Pass | C11: Pass | D11: Not run | E11: {} | F11: {} | G11: 2026-10-05T07:38:22.125Z 2026-10-05T07:44:17.498Z
A12: TC-NFR-SEC-05 | B12: Pass | C12: Pass | D12: Not run | E12: {} | F12: {} | G12: 2026-10-05T07:38:22.125Z 2026-10-05T07:44:17.498Z
A13: TC-NFR-SEC-06 | B13: Pass | C13: Pass | D13: Not run | E13: {} | F13: {} | G13: 2026-10-05T07:38:22.125Z 2026-10-05T07:44:17.498Z
A14: TC-NFR-SEC-07 | B14: Fail | C14: Fail | D14: Not run | E14: { "attemptedStatus": 200, "foreignWritePersisted": true } | F14: { "attemptedStatus": 200, "foreignWritePersisted": true } | G14: 2026-10-05T07:38:22.125Z 2026-10-05T07:44:17.498Z | H14: BOLA: foreign coach write accepted or persisted; HTTP=200, persisted=true BOLA: foreign coach write accepted or persisted; HTTP=200, persisted=true. Expression: ((r.status in [403, 404]) && observations.foreignWritePersisted)
A15: TC-NFR-SEC-08 | B15: Pass | C15: Pass | D15: Not run | E15: {} | F15: {} | G15: 2026-10-05T07:38:22.125Z 2026-10-05T07:44:17.498Z
A16: TC-NFR-SEC-09 | B16: Pass | C16: Pass | D16: Not run | E16: {} | F16: {} | G16: 2026-10-05T07:38:22.125Z 2026-10-05T07:44:17.498Z
A17: TC-NFR-SEC-10 | B17: Fail | C17: Fail | D17: Not run | E17: { "unknownStatus": 401, "knownStatus": 401, "unknownMessage": "Incorrect email or password.", "knownMessage": "Incorrect password. 4 attempt(s) remaining." } | F17: { "unknownStatus": 401, "knownStatus": 401, "unknownMessage": "Incorrect email or password.", "knownMessage": "Incorrect password. 4 attempt(s) remaining." } | G17: 2026-10-05T07:38:22.125Z 2026-10-05T07:44:17.498Z | H17: PROPOSED policy: account enumeration via different error messages + actual - expected + 'Incorrect email or password.' - 'Incorrect password. 4 attempt(s) remaining.' ^ PROPOSED policy: account enumeration via different error messages. Expression: (unknown.data.message == known.data.message)
A18: TC-NFR-SEC-11 | B18: Fail | C18: Fail | D18: Not run | E18: { "attempts": 25, "throttled": false, "retryAfter": null } | F18: { "attempts": 25, "throttled": false, "retryAfter": null } | G18: 2026-10-05T07:38:22.125Z 2026-10-05T07:44:17.498Z | H18: PROPOSED lab anti-abuse policy: no 429 in bounded 25-request login burst PROPOSED lab anti-abuse policy: no 429 in bounded 25-request login burst. Expression: (limited != null). Values: limited = null

Sheet NFR Defects
A1: ID | B1: Case | C1: Severity | D1: Policy / expected | E1: Actual evidence | F1: Source | G1: Recommendation | H1: Status / qualification
A2: NFR-BUG-001 | B2: TC-NFR-SEC-07 | C2: High | D2: Session write must verify planning.coach_id. Reuse owner seed planning; create new QA session 201; foreign coach POST 403/404; seanceRealisee remains null. | E2: {"attemptedStatus":200,"foreignWritePersisted":true} BOLA: foreign coach write accepted or persisted; HTTP=200, persisted=true | F2: backend/app/Http/Controllers/Coach/PlanningController.php::marquerRealisee | G2: Verify session planning coach ownership BEFORE updateOrCreate; reject 403/404. | H2: Detected in isolated lab; application NOT changed.
A3: NFR-BUG-002 | B3: TC-NFR-SEC-10 | C3: Medium | D3: PROPOSED: invalid credentials should have indistinguishable public status/message. Unknown email and wrong password on QA account both 401 with identical message; this is not a timing side-channel test. | E3: {"unknownStatus":401,"knownStatus":401,"unknownMessage":"Incorrect email or password.","knownMessage":"Incorrect password. 4 attempt(s) remaining."} PROPOSED policy: account enumeration via different error messages + actual - expected + 'Incorrect email or password.' - 'Incorrect password. 4 attempt(s) remaining.' ^ | F3: backend/app/Http/Controllers/Auth/AuthController.php::login | G3: Use generic invalid-credential public message; assess timing behavior separately. | H3: Detected in isolated lab; application NOT changed. Proposed policy gap; confirm requirements with team.
A4: NFR-BUG-003 | B4: TC-NFR-SEC-11 | C4: Medium (proposed) | D4: PROPOSED LAB policy: <=20 failed login attempts/minute/source; 429 by request 25. At most 25 sequential attempts with nonexistent unique email; at least one 429 and positive Retry-After. No real user lockout. | E4: {"attempts":25,"throttled":false,"retryAfter":null} PROPOSED lab anti-abuse policy: no 429 in bounded 25-request login burst | F4: backend/routes/api.php (login has no throttle middleware) | G4: Agree rate-limit policy; add throttle with persistent cache store for deployment, Retry-After and review reset/register routes. | H4: Detected in isolated lab; application NOT changed. Proposed policy gap; confirm requirements with team.
